{"ability":"Nen","alchemist":"Edward Elric","anime":"Cowboy Bebop","antagonist":"Frieza","arc":"Chimera Ant Arc","armor":"Saints' Cloths","attack":"Getsuga Tenshou","baka":"Common insult","blessing":"Aqua's Purification","catchphrase":"Plus Ultra!","character":"Lelouch vi Britannia","city":"Neo-Tokyo","composer":"Yoko Kanno","concept":"Alchemy","creature":"Totoro","curse":"The Curse of Ymir","cyborg":"Genos","demon":"Nezuko Kamado","detective":"L Lawliet","dimension":"Hueco Mundo","director":"Satoshi Kon","drink":"Dr. Pepper","element":"Hamon","emotion":"Yandere","ending":"Fly Me To The Moon","episode":"The Beach Episode","family":"Zoldyck Family","festival":"School Culture Festival","filler":"Goku's Driving Test","finale":"The End of Evangelion","flashback":"Itachi's Backstory","food":"Onigiri","genre":"Shounen","god":"Beerus","government":"World Government","guild":"Fairy Tail","gun":"The Dominator","hairstyle":"Ahoge","hero":"All Might","honorific":"Senpai","hunter":"Gon Freecss","idol":"Ai Hoshino","item":"Death Note","kaiju":"Godzilla","king":"Meruem","kouhai":"Mash Kyrielight","location":"Soul Society","mage":"Megumin","manga":"Berserk","mangaka":"Kentaro Miura","mascot":"Pikachu","mcguffin":"Philosopher's Stone","mecha":"Evangelion Unit-01","movie":"Your Name","music":"Tank!","nakama":"Straw Hat Pirates","ninja":"Kakashi Hatake","opening":"A Cruel Angel's Thesis","organization":"Akatsuki","ova":"Hellsing Ultimate","pact":"Faustian Contract","pet":"Happy","pilot":"Shinji Ikari","pirate":"Monkey D. Luffy","planet":"Namek","power":"Kamehameha","princess":"Mononoke","prophecy":"Child of Prophecy","protagonist":"Saitama","quest":"Finding the One Piece","quirk":"One For All","quote":"Omae wa mou shindeiru.","race":"Saiyan","rival":"Vegeta","robot":"Astro Boy","saga":"Frieza Saga","samurai":"Roronoa Zoro","school":"U.A. High School","sensei":"Master Roshi","ship":"Going Merry","sidekick":"Krillin","spell":"Explosion!","spirit":"Ryuk","stand":"Star Platinum","studio":"Studio Ghibli","sugoi":"Exclamation of awe","sword":"Excalibur","team":"Phantom Troupe","technique":"Rasengan","term":"Kawaii","titan":"Armored Titan","tournament":"Dark Tournament","transformation":"Super Saiyan","trope":"Isekai","vehicle":"Kaneda's Bike","village":"Konohagakure","villain":"Dio Brando","war":"Fourth Great Ninja War","weapon":"Zanpakuto","yokai":"InuYasha","zip":"the zip"}